cellosaurus_mcp/__init__.py
cellosaurus_mcp/client.py
cellosaurus_mcp/main.py
cellosaurus_mcp/mcp.py
cellosaurus_mcp/models.py
cellosaurus_mcp/tools/__init__.py
cellosaurus_mcp/tools/cellosaurus_tools.py
cellosaurus_mcp-0.0.1.dist-info/METADATA
cellosaurus_mcp-0.0.1.dist-info/WHEEL
cellosaurus_mcp-0.0.1.dist-info/entry_points.txt
cellosaurus_mcp-0.0.1.dist-info/licenses/LICENSE
cellosaurus_mcp-0.0.1.dist-info/RECORD
