Metadata-Version: 2.4
Name: cellosaurus_mcp
Version: 0.0.1
Summary: Unofficial MCP server for the SIB Cellosaurus resource.
Project-URL: Documentation, https://unofficial-cellosaurus-mcp.readthedocs.io/
Project-URL: Homepage, https://github.com/biocontext-ai/unofficial-cellosaurus-mcp
Project-URL: Source, https://github.com/biocontext-ai/unofficial-cellosaurus-mcp
Author: Malte Kuehl
Maintainer-email: Malte Kuehl <malte.kuehl@clin.au.dk>
License: 
License-File: LICENSE
Classifier: Programming Language :: Python :: 3 :: Only
Classifier: Programming Language :: Python :: 3.11
Classifier: Programming Language :: Python :: 3.12
Classifier: Programming Language :: Python :: 3.13
Requires-Python: >=3.11
Requires-Dist: click
Requires-Dist: fastmcp>=0.15.0
Requires-Dist: httpx<=0.29.0,>=0.28.0
Requires-Dist: pydantic>=2.0.0
Provides-Extra: dev
Requires-Dist: pre-commit; extra == 'dev'
Requires-Dist: twine>=4.0.2; extra == 'dev'
Provides-Extra: doc
Requires-Dist: docutils!=0.18.*,!=0.19.*,>=0.8; extra == 'doc'
Requires-Dist: ipykernel; extra == 'doc'
Requires-Dist: ipython; extra == 'doc'
Requires-Dist: myst-nb>=1.1; extra == 'doc'
Requires-Dist: pandas; extra == 'doc'
Requires-Dist: setuptools; extra == 'doc'
Requires-Dist: sphinx-autodoc-typehints; extra == 'doc'
Requires-Dist: sphinx-book-theme>=1; extra == 'doc'
Requires-Dist: sphinx-copybutton; extra == 'doc'
Requires-Dist: sphinx-tabs; extra == 'doc'
Requires-Dist: sphinx>=8.1; extra == 'doc'
Requires-Dist: sphinxext-opengraph; extra == 'doc'
Provides-Extra: test
Requires-Dist: coverage>=7.0.0; extra == 'test'
Requires-Dist: httpx-sse>=0.3.0; extra == 'test'
Requires-Dist: pytest-asyncio>=0.21.0; extra == 'test'
Requires-Dist: pytest-mock>=3.10.0; extra == 'test'
Requires-Dist: pytest>=7.0.0; extra == 'test'
